azure_key_vault_report/__init__.py
azure_key_vault_report/alerts.py
azure_key_vault_report/azure_key_vault_report.py
azure_key_vault_report/config.py
azure_key_vault_report/set_timestamp.py
ops_py_azure_key_vault_report-8.0.2.dist-info/licenses/LICENSE
ops_py_azure_key_vault_report-8.0.2.dist-info/METADATA
ops_py_azure_key_vault_report-8.0.2.dist-info/WHEEL
ops_py_azure_key_vault_report-8.0.2.dist-info/top_level.txt
ops_py_azure_key_vault_report-8.0.2.dist-info/RECORD
