Metadata-Version: 2.4
Name: ops-py-azure-key-vault-report
Version: 8.0.2
Summary: Output a Key Vault Secrets report
License: MIT License
License-File: LICENSE
Dynamic: license-file
